hmile/DataExporter.py
hmile/DataProvider.py
hmile/DataTransformer.py
hmile/Exception.py
hmile/FillPolicy.py
hmile/__init__.py
hmile/__version__.py
hmile/utils.py
hmile-0.5.1.dist-info/METADATA
hmile-0.5.1.dist-info/WHEEL
hmile-0.5.1.dist-info/top_level.txt
hmile-0.5.1.dist-info/RECORD
