Metadata-Version: 2.1
Name: hmile
Version: 0.5.1
Summary: Python 3.x module to render financial results in tensorboard 
Home-page: https://github.com/theophane-droid/8miles-render
Author: theophanedroid
Author-email: theodesile@gmail.com
License: MIT license
Project-URL: Bug Tracker, https://github.com/theophane-droid/8miles-render/issues
Classifier: Programming Language :: Python :: 3
Classifier: License :: OSI Approved :: MIT License
Classifier: Operating System :: OS Independent
Requires-Python: >=3.9
Requires-Dist: ta (>=0.10.2)
Requires-Dist: pandas (~=1.5.3)
Requires-Dist: elasticsearch (>=8.6.2)
Requires-Dist: numpy (>=1.24.2)
Requires-Dist: yfinance (>=0.1.74)
Requires-Dist: ta-lib (>=0.4.25)
Requires-Dist: pandas-ta (>=0.3.14b0)
Requires-Dist: requests (>=2.28.1)
Requires-Dist: pyyaml (>=6.0)
Requires-Dist: scipy (>=1.10.1)
Provides-Extra: test
Requires-Dist: unittest2 ; extra == 'test'
